[{"id": 3, "name": "superb electrical", "price": 140.15, "quantity": 584, "category": "tools", "fromCity": "Тбилиси", "isAvailable": "1", "views": 3812, "version": 34}, {"id": 130, "name": "delightful nail file", "price": 26.450000000000003, "quantity": 90, "category": "cosmetics", "fromCity": "Артейхо", "isAvailable": "1", "views": 31708, "version": 28}, {"id": 34, "name": "refined pedicure set", "price": 12.47, "quantity": 794, "category": "cosmetics", "fromCity": "Тарраса", "isAvailable": "1", "views": 75804, "version": 26}, {"id": 36, "name": "refined cranberry", "price": 472.338, "quantity": 636, "category": "fruit", "fromCity": "Виго", "isAvailable": "1", "views": 14816, "version": 26}, {"id": 89, "name": "elegant scaffolding", "price": 64.87, "quantity": 1133, "category": "tools", "fromCity": "Осера", "isAvailable": "1", "views": 43277, "version": 24}, {"id": 115, "name": "pleasant night cream", "price": 36.83, "quantity": 862, "category": "cosmetics", "fromCity": "Бишкек", "isAvailable": "1", "views": 83493, "version": 24}, {"id": 127, "name": "amazing mango", "price": 39.4, "quantity": 1018, "category": "fruit", "fromCity": "Сория", "isAvailable": "0", "views": 95932, "version": 24}, {"id": 68, "name": "superb nail polish", "price": 266.688, "quantity": 129, "category": "cosmetics", "fromCity": "Касерес", "isAvailable": "1", "views": 48289, "version": 22}, {"id": 105, "name": "tasteful blackberry", "price": 46.89, "quantity": 820, "category": "fruit", "fromCity": "Тарраса", "isAvailable": "1", "views": 68608, "version": 20}, {"id": 54, "name": "AMD Ryzen 5", "price": 140032.65, "quantity": 25, "category": "no", "fromCity": "Любляна", "isAvailable": "0", "views": 88337, "version": 18}]